auto_notion_py/__init__.py
auto_notion_py/github/__init__.py
auto_notion_py/github/api.py
auto_notion_py/notion/__init__.py
auto_notion_py/notion/api.py
auto_notion_py/notion/markdown_converter/__init__.py
auto_notion_py/notion/markdown_converter/converter.py
auto_notion_py/notion/markdown_converter/plotly.py
auto_notion_py/notion/markdown_converter/renderer.py
auto_notion_py/notion/markdown_converter/uploader.py
auto_notion_py/notion/page_client/__init__.py
auto_notion_py/notion/page_client/block.py
auto_notion_py/notion/page_client/client.py
auto_notion_py/notion/page_client/collection.py
auto_notion_py/notion/page_client/logger.py
auto_notion_py/notion/page_client/maps.py
auto_notion_py/notion/page_client/markdown.py
auto_notion_py/notion/page_client/monitor.py
auto_notion_py/notion/page_client/operations.py
auto_notion_py/notion/page_client/records.py
auto_notion_py/notion/page_client/settings.py
auto_notion_py/notion/page_client/smoke_test.py
auto_notion_py/notion/page_client/space.py
auto_notion_py/notion/page_client/store.py
auto_notion_py/notion/page_client/user.py
auto_notion_py/notion/page_client/utils.py
auto_notion_py/zotero/api.py
auto_notion_py-0.1.4.dist-info/entry_points.txt
auto_notion_py-0.1.4.dist-info/WHEEL
auto_notion_py-0.1.4.dist-info/METADATA
auto_notion_py-0.1.4.dist-info/RECORD
