Metadata-Version: 2.1
Name: auto-notion-py
Version: 0.1.4
Summary: Notion automation package
Author: Piotr Styczyński
Author-email: pstyczynski@sumologic.com
Requires-Python: >=3.8,<4.0
Classifier: Programming Language :: Python :: 3
Classifier: Programming Language :: Python :: 3.10
Classifier: Programming Language :: Python :: 3.8
Classifier: Programming Language :: Python :: 3.9
Requires-Dist: PyGithub (>=1.55,<2.0)
Requires-Dist: aiomultiprocess (>=0.9.0,<0.10.0)
Requires-Dist: bs4 (>=0.0.1,<0.0.2)
Requires-Dist: cached-property (>=1.5.2,<2.0.0)
Requires-Dist: chart-studio (>=1.1.0,<2.0.0)
Requires-Dist: commonmark (>=0.9.1,<0.10.0)
Requires-Dist: dictdiffer (>=0.9.0,<0.10.0)
Requires-Dist: githubpy (>=1.1.0,<2.0.0)
Requires-Dist: jupyter (>=1.0.0,<2.0.0)
Requires-Dist: matplotlib (>=3.5.1,<4.0.0)
Requires-Dist: mistletoe (>=0.8.2,<0.9.0)
Requires-Dist: moment (>=0.12.1,<0.13.0)
Requires-Dist: notion-client (>=0.8.0,<0.9.0)
Requires-Dist: pandas (>=1.3.5,<2.0.0)
Requires-Dist: plotly (>=5.6.0,<6.0.0)
Requires-Dist: python-slugify (>=6.1.1,<7.0.0)
Requires-Dist: pyzotero (>=1.5.1,<2.0.0)
Requires-Dist: requests (>=2.27.1,<3.0.0)
Requires-Dist: tzlocal (>=4.2,<5.0)
